{"v":4,"entries":{"example-introduction--docs":{"id":"example-introduction--docs","title":"Example/Introduction","name":"Docs","importPath":"./src/stories/Introduction.stories.mdx","type":"docs","tags":["stories-mdx","docs","autodocs"],"storiesImports":[]},"components-ui-alert--docs":{"id":"components-ui-alert--docs","title":"Components/ui-alert","name":"Docs","importPath":"./src/components/ui-alert/ui-alert.stories.ts","type":"docs","tags":["docs","autodocs"],"storiesImports":[]},"components-ui-alert--default":{"id":"components-ui-alert--default","title":"Components/ui-alert","name":"Default","importPath":"./src/components/ui-alert/ui-alert.stories.ts","tags":["story"],"type":"story"},"components-ui-badge--docs":{"id":"components-ui-badge--docs","title":"Components/ui-badge","name":"Docs","importPath":"./src/components/ui-badge/ui-badge.stories.ts","type":"docs","tags":["docs","autodocs"],"storiesImports":[]},"components-ui-badge--default":{"id":"components-ui-badge--default","title":"Components/ui-badge","name":"Default","importPath":"./src/components/ui-badge/ui-badge.stories.ts","tags":["story"],"type":"story"},"components-ui-ber-rank--docs":{"id":"components-ui-ber-rank--docs","title":"Components/ui-ber-rank","name":"Docs","importPath":"./src/components/ui-ber-rank/ui-ber-rank.stories.ts","type":"docs","tags":["docs","autodocs"],"storiesImports":[]},"components-ui-ber-rank--default":{"id":"components-ui-ber-rank--default","title":"Components/ui-ber-rank","name":"Default","importPath":"./src/components/ui-ber-rank/ui-ber-rank.stories.ts","tags":["story"],"type":"story"},"components-ui-button--docs":{"id":"components-ui-button--docs","title":"Components/ui-button","name":"Docs","importPath":"./src/components/ui-button/ui-button.stories.ts","type":"docs","tags":["docs","autodocs"],"storiesImports":[]},"components-ui-button--primary":{"id":"components-ui-button--primary","title":"Components/ui-button","name":"Primary","importPath":"./src/components/ui-button/ui-button.stories.ts","tags":["story"],"type":"story"},"components-ui-button--buttons":{"id":"components-ui-button--buttons","title":"Components/ui-button","name":"Buttons","importPath":"./src/components/ui-button/ui-button.stories.ts","tags":["story"],"type":"story"},"components-ui-card-cta--docs":{"id":"components-ui-card-cta--docs","title":"Components/ui-card-cta","name":"Docs","importPath":"./src/components/ui-card-cta/ui-card-cta.stories.ts","type":"docs","tags":["docs","autodocs"],"storiesImports":[]},"components-ui-card-cta--default":{"id":"components-ui-card-cta--default","title":"Components/ui-card-cta","name":"Default","importPath":"./src/components/ui-card-cta/ui-card-cta.stories.ts","tags":["story"],"type":"story"},"components-ui-card-result--docs":{"id":"components-ui-card-result--docs","title":"Components/ui-card-result","name":"Docs","importPath":"./src/components/ui-card-result/ui-card-result.stories.ts","type":"docs","tags":["docs","autodocs"],"storiesImports":[]},"components-ui-card-result--default":{"id":"components-ui-card-result--default","title":"Components/ui-card-result","name":"Default","importPath":"./src/components/ui-card-result/ui-card-result.stories.ts","tags":["story"],"type":"story"},"components-ui-card-simple--docs":{"id":"components-ui-card-simple--docs","title":"Components/ui-card-simple","name":"Docs","importPath":"./src/components/ui-card-simple/ui-card-simple.stories.ts","type":"docs","tags":["docs","autodocs"],"storiesImports":[]},"components-ui-card-simple--default":{"id":"components-ui-card-simple--default","title":"Components/ui-card-simple","name":"Default","importPath":"./src/components/ui-card-simple/ui-card-simple.stories.ts","tags":["story"],"type":"story"},"components-ui-checkbox--docs":{"id":"components-ui-checkbox--docs","title":"Components/ui-checkbox","name":"Docs","importPath":"./src/components/ui-checkbox/ui-checkbox.stories.ts","type":"docs","tags":["docs","autodocs"],"storiesImports":[]},"components-ui-checkbox--default":{"id":"components-ui-checkbox--default","title":"Components/ui-checkbox","name":"Default","importPath":"./src/components/ui-checkbox/ui-checkbox.stories.ts","tags":["story"],"type":"story"},"components-ui-icon-wrapper--docs":{"id":"components-ui-icon-wrapper--docs","title":"Components/ui-icon-wrapper","name":"Docs","importPath":"./src/components/ui-icon-wrapper/ui-icon-wrapper.stories.ts","type":"docs","tags":["docs","autodocs"],"storiesImports":[]},"components-ui-icon-wrapper--default":{"id":"components-ui-icon-wrapper--default","title":"Components/ui-icon-wrapper","name":"Default","importPath":"./src/components/ui-icon-wrapper/ui-icon-wrapper.stories.ts","tags":["story"],"type":"story"},"components-ui-icon--docs":{"id":"components-ui-icon--docs","title":"Components/ui-icon","name":"Docs","importPath":"./src/components/ui-icon/ui-icon.stories.ts","type":"docs","tags":["docs","autodocs"],"storiesImports":[]},"components-ui-icon--default":{"id":"components-ui-icon--default","title":"Components/ui-icon","name":"Default","importPath":"./src/components/ui-icon/ui-icon.stories.ts","tags":["story"],"type":"story"},"components-ui-input-range--docs":{"id":"components-ui-input-range--docs","title":"Components/ui-input-range","name":"Docs","importPath":"./src/components/ui-input-range/ui-input-range.stories.ts","type":"docs","tags":["docs","autodocs"],"storiesImports":[]},"components-ui-input-range--default":{"id":"components-ui-input-range--default","title":"Components/ui-input-range","name":"Default","importPath":"./src/components/ui-input-range/ui-input-range.stories.ts","tags":["story"],"type":"story"},"components-ui-input--docs":{"id":"components-ui-input--docs","title":"Components/ui-input","name":"Docs","importPath":"./src/components/ui-input/ui-input.stories.ts","type":"docs","tags":["docs","autodocs"],"storiesImports":[]},"components-ui-input--default":{"id":"components-ui-input--default","title":"Components/ui-input","name":"Default","importPath":"./src/components/ui-input/ui-input.stories.ts","tags":["story"],"type":"story"},"components-ui-input--all-inputs":{"id":"components-ui-input--all-inputs","title":"Components/ui-input","name":"All Inputs","importPath":"./src/components/ui-input/ui-input.stories.ts","tags":["story"],"type":"story"},"components-ui-list-item--docs":{"id":"components-ui-list-item--docs","title":"Components/ui-list-item","name":"Docs","importPath":"./src/components/ui-list-item/ui-list-item.stories.ts","type":"docs","tags":["docs","autodocs"],"storiesImports":[]},"components-ui-list-item--default":{"id":"components-ui-list-item--default","title":"Components/ui-list-item","name":"Default","importPath":"./src/components/ui-list-item/ui-list-item.stories.ts","tags":["story"],"type":"story"},"components-ui-modal--docs":{"id":"components-ui-modal--docs","title":"Components/ui-modal","name":"Docs","importPath":"./src/components/ui-modal/ui-modal.stories.ts","type":"docs","tags":["docs","autodocs"],"storiesImports":[]},"components-ui-modal--default":{"id":"components-ui-modal--default","title":"Components/ui-modal","name":"Default","importPath":"./src/components/ui-modal/ui-modal.stories.ts","tags":["story"],"type":"story"},"components-ui-notification-badge--docs":{"id":"components-ui-notification-badge--docs","title":"Components/ui-notification-badge","name":"Docs","importPath":"./src/components/ui-notification-badge/ui-notification-badge.stories.ts","type":"docs","tags":["docs","autodocs"],"storiesImports":[]},"components-ui-notification-badge--default":{"id":"components-ui-notification-badge--default","title":"Components/ui-notification-badge","name":"Default","importPath":"./src/components/ui-notification-badge/ui-notification-badge.stories.ts","tags":["story"],"type":"story"},"components-ui-order-card--docs":{"id":"components-ui-order-card--docs","title":"Components/ui-order-card","name":"Docs","importPath":"./src/components/ui-order-card/ui-order-card.stories.ts","type":"docs","tags":["docs","autodocs"],"storiesImports":[]},"components-ui-order-card--default":{"id":"components-ui-order-card--default","title":"Components/ui-order-card","name":"Default","importPath":"./src/components/ui-order-card/ui-order-card.stories.ts","tags":["story"],"type":"story"},"components-ui-plain-radio--docs":{"id":"components-ui-plain-radio--docs","title":"Components/ui-plain-radio","name":"Docs","importPath":"./src/components/ui-plain-radio/ui-plain-radio.stories.ts","type":"docs","tags":["docs","autodocs"],"storiesImports":[]},"components-ui-plain-radio--default":{"id":"components-ui-plain-radio--default","title":"Components/ui-plain-radio","name":"Default","importPath":"./src/components/ui-plain-radio/ui-plain-radio.stories.ts","tags":["story"],"type":"story"},"components-ui-radio-fancy--docs":{"id":"components-ui-radio-fancy--docs","title":"Components/ui-radio-fancy","name":"Docs","importPath":"./src/components/ui-radio-fancy/ui-radio-fancy.stories.ts","type":"docs","tags":["docs","autodocs"],"storiesImports":[]},"components-ui-radio-fancy--default":{"id":"components-ui-radio-fancy--default","title":"Components/ui-radio-fancy","name":"Default","importPath":"./src/components/ui-radio-fancy/ui-radio-fancy.stories.ts","tags":["story"],"type":"story"},"components-ui-radio--docs":{"id":"components-ui-radio--docs","title":"Components/ui-radio","name":"Docs","importPath":"./src/components/ui-radio/ui-radio.stories.ts","type":"docs","tags":["docs","autodocs"],"storiesImports":[]},"components-ui-radio--default":{"id":"components-ui-radio--default","title":"Components/ui-radio","name":"Default","importPath":"./src/components/ui-radio/ui-radio.stories.ts","tags":["story"],"type":"story"},"components-ui-result-card-range--docs":{"id":"components-ui-result-card-range--docs","title":"Components/ui-result-card-range","name":"Docs","importPath":"./src/components/ui-result-card-range/ui-result-card-range.stories.ts","type":"docs","tags":["docs","autodocs"],"storiesImports":[]},"components-ui-result-card-range--single-card":{"id":"components-ui-result-card-range--single-card","title":"Components/ui-result-card-range","name":"Single Card","importPath":"./src/components/ui-result-card-range/ui-result-card-range.stories.ts","tags":["story"],"type":"story"},"components-ui-result-card-range--full-card":{"id":"components-ui-result-card-range--full-card","title":"Components/ui-result-card-range","name":"Full Card","importPath":"./src/components/ui-result-card-range/ui-result-card-range.stories.ts","tags":["story"],"type":"story"},"components-ui-ripple--docs":{"id":"components-ui-ripple--docs","title":"Components/ui-ripple","name":"Docs","importPath":"./src/components/ui-ripple/ui-ripple.stories.ts","type":"docs","tags":["docs","autodocs"],"storiesImports":[]},"components-ui-ripple--default":{"id":"components-ui-ripple--default","title":"Components/ui-ripple","name":"Default","importPath":"./src/components/ui-ripple/ui-ripple.stories.ts","tags":["story"],"type":"story"},"components-ui-ripple--with-button":{"id":"components-ui-ripple--with-button","title":"Components/ui-ripple","name":"With Button","importPath":"./src/components/ui-ripple/ui-ripple.stories.ts","tags":["story"],"type":"story"},"components-ui-select--docs":{"id":"components-ui-select--docs","title":"Components/ui-select","name":"Docs","importPath":"./src/components/ui-select/ui-select.stories.ts","type":"docs","tags":["docs","autodocs"],"storiesImports":[]},"components-ui-select--default":{"id":"components-ui-select--default","title":"Components/ui-select","name":"Default","importPath":"./src/components/ui-select/ui-select.stories.ts","tags":["story"],"type":"story"},"components-ui-snackbar--docs":{"id":"components-ui-snackbar--docs","title":"Components/ui-snackbar","name":"Docs","importPath":"./src/components/ui-snackbar/ui-snackbar.stories.ts","type":"docs","tags":["docs","autodocs"],"storiesImports":[]},"components-ui-snackbar--default":{"id":"components-ui-snackbar--default","title":"Components/ui-snackbar","name":"Default","importPath":"./src/components/ui-snackbar/ui-snackbar.stories.ts","tags":["story"],"type":"story"},"components-ui-table--docs":{"id":"components-ui-table--docs","title":"Components/ui-table","name":"Docs","importPath":"./src/components/ui-table/ui-table.stories.ts","type":"docs","tags":["docs","autodocs"],"storiesImports":[]},"components-ui-table--default":{"id":"components-ui-table--default","title":"Components/ui-table","name":"Default","importPath":"./src/components/ui-table/ui-table.stories.ts","tags":["story"],"type":"story"},"components-ui-tabs--docs":{"id":"components-ui-tabs--docs","title":"Components/ui-tabs","name":"Docs","importPath":"./src/components/ui-tabs/ui-tabs.stories.ts","type":"docs","tags":["docs","autodocs"],"storiesImports":[]},"components-ui-tabs--default":{"id":"components-ui-tabs--default","title":"Components/ui-tabs","name":"Default","importPath":"./src/components/ui-tabs/ui-tabs.stories.ts","tags":["story"],"type":"story"},"components-ui-toggle--docs":{"id":"components-ui-toggle--docs","title":"Components/ui-toggle","name":"Docs","importPath":"./src/components/ui-toggle/ui-toggle.stories.ts","type":"docs","tags":["docs","autodocs"],"storiesImports":[]},"components-ui-toggle--default":{"id":"components-ui-toggle--default","title":"Components/ui-toggle","name":"Default","importPath":"./src/components/ui-toggle/ui-toggle.stories.ts","tags":["story"],"type":"story"},"components-ui-typography--docs":{"id":"components-ui-typography--docs","title":"Components/ui-typography","name":"Docs","importPath":"./src/components/ui-typography/ui-typography.stories.ts","type":"docs","tags":["docs","autodocs"],"storiesImports":[]},"components-ui-typography--default":{"id":"components-ui-typography--default","title":"Components/ui-typography","name":"Default","importPath":"./src/components/ui-typography/ui-typography.stories.ts","tags":["story"],"type":"story"},"components-ui-verification-input--docs":{"id":"components-ui-verification-input--docs","title":"Components/ui-verification-input","name":"Docs","importPath":"./src/components/ui-verification-input/ui-verification-input.stories.ts","type":"docs","tags":["docs","autodocs"],"storiesImports":[]},"components-ui-verification-input--default":{"id":"components-ui-verification-input--default","title":"Components/ui-verification-input","name":"Default","importPath":"./src/components/ui-verification-input/ui-verification-input.stories.ts","tags":["story"],"type":"story"},"example-colors--docs":{"id":"example-colors--docs","title":"Example/Colors","name":"Docs","importPath":"./src/stories/colors/colors.stories.ts","type":"docs","tags":["docs","autodocs"],"storiesImports":[]},"example-colors--colors":{"id":"example-colors--colors","title":"Example/Colors","name":"Colors","importPath":"./src/stories/colors/colors.stories.ts","tags":["story"],"type":"story"},"example-fontsizes--docs":{"id":"example-fontsizes--docs","title":"Example/FontSizes","name":"Docs","importPath":"./src/stories/font-sizes/font-sizes.stories.ts","type":"docs","tags":["docs","autodocs"],"storiesImports":[]},"example-fontsizes--font-sizes":{"id":"example-fontsizes--font-sizes","title":"Example/FontSizes","name":"Font Sizes","importPath":"./src/stories/font-sizes/font-sizes.stories.ts","tags":["story"],"type":"story"},"example-spacings--docs":{"id":"example-spacings--docs","title":"Example/Spacings","name":"Docs","importPath":"./src/stories/spacings/spacings.stories.ts","type":"docs","tags":["docs","autodocs"],"storiesImports":[]},"example-spacings--spacings":{"id":"example-spacings--spacings","title":"Example/Spacings","name":"Spacings","importPath":"./src/stories/spacings/spacings.stories.ts","tags":["story"],"type":"story"}}}
